sweap_cli/__init__.py
sweap_cli/__main__.py
sweap_cli/api_client.py
sweap_cli/evaluation.py
sweap_cli/main.py
sweap_cli/manifest_utils.py
sweap_cli/modal_runner.py
sweap_cli/runners/__init__.py
sweap_cli/runners/base.py
sweap_cli/runners/gradle_runner.py
sweap_cli/runners/maven_runner.py
sweap_cli/runners/node_runner.py
sweap_cli/runners/pytest_runner.py
sweap_cli-0.1.9.dist-info/METADATA
sweap_cli-0.1.9.dist-info/WHEEL
sweap_cli-0.1.9.dist-info/entry_points.txt
sweap_cli-0.1.9.dist-info/top_level.txt
sweap_cli-0.1.9.dist-info/RECORD
