Metadata-Version: 2.4
Name: sweap-cli
Version: 0.1.9
Summary: CLI for authoring and running SWEAP benchmark tasks
Author: SWEAP Team
Requires-Python: >=3.10
Requires-Dist: typer>=0.9
Requires-Dist: pydantic>=2.6
Requires-Dist: rich>=13.7
Requires-Dist: modal>=0.62
Requires-Dist: fastapi>=0.111
Requires-Dist: uvicorn[standard]>=0.23
Requires-Dist: httpx>=0.27
Requires-Dist: pydantic-settings>=2.3
Requires-Dist: PyJWT>=2.8
